CHANGES
LICENSE
MANIFEST.in
README.rst
setup.cfg
setup.py
tox.ini
docs/Makefile
docs/api.rst
docs/conf.py
docs/contributing.rst
docs/index.rst
docs/logging.rst
docs/quickstart.rst
docs/recipes.rst
docs/_static/empty
pyramid_uniform/__init__.py
pyramid_uniform.egg-info/PKG-INFO
pyramid_uniform.egg-info/SOURCES.txt
pyramid_uniform.egg-info/dependency_links.txt
pyramid_uniform.egg-info/not-zip-safe
pyramid_uniform.egg-info/requires.txt
pyramid_uniform.egg-info/top_level.txt
pyramid_uniform/tests/__init__.py
pyramid_uniform/tests/test_form.py
pyramid_uniform/tests/test_renderer.py
pyramid_uniform/tests/utils.py