Metadata-Version: 1.1
Name: pyramid-uniform
Version: 0.3.2
Summary: Form handling for Pyramid.
Home-page: http://github.com/cartlogic/pyramid_uniform
Author: Scott Torborg
Author-email: scott@cartlogic.com
License: MIT
Keywords: pyramid forms validation rendering
Platform: UNKNOWN
Classifier: Development Status :: 3 - Alpha
Classifier: License :: OSI Approved :: MIT License
Classifier: Programming Language :: Python :: 2
Classifier: Programming Language :: Python :: 2.7
Classifier: Programming Language :: Python :: 3
Classifier: Programming Language :: Python :: 3.3
Classifier: Programming Language :: Python :: 3.4
Classifier: Framework :: Pyramid
